{
    "expected_value": 64.0543,
    "optimal_gammas": [
        4.8504768918609935,
        0.9136982304944237,
        4.084840373540988,
        1.7539279342707064,
        4.247314650073294,
        1.952969055815817,
        3.569086511671778
    ],
    "optimal_betas": [
        1.67067414382847,
        3.1256676852932843,
        1.9596005043150677,
        2.999095902798441,
        0.5131732534653977,
        1.1277618684799817,
        1.6865657933099099
    ],
    "problem_identifier": "{'W': [1, 1], 'W_max': 2, 'A': 32, 'B': 4, 'C': 128}",
    "now": "2021-05-07 02:04:59",
    "execution_time": "0:49:31.703307",
    "nfev": 1575,
    "message": "Optimization terminated successfully.",
    "success": true,
    "nit": 5,
    "problem": {
        "W": [
            1,
            1
        ],
        "W_max": 2,
        "A": 32,
        "B": 4,
        "C": 128
    },
    "optimal_cost": 1.0,
    "probability_distribution": {
        "64.0": 0.0029,
        "40.0": 0.0158,
        "97.0": 0.0174,
        "41.0": 0.040999999999999995,
        "1.0": 0.008799999999999999,
        "73.0": 0.0519,
        "81.0": 0.015799999999999998,
        "17.0": 0.0153,
        "65.0": 0.0275,
        "33.0": 0.0172,
        "9.0": 0.0235,
        "49.0": 0.030100000000000002,
        "105.0": 0.0095,
        "32.0": 0.0086,
        "140.0": 0.0063,
        "68.0": 0.013600000000000001,
        "12.0": 0.005900000000000001,
        "116.0": 0.0127,
        "108.0": 0.0292,
        "44.0": 0.0141,
        "52.0": 0.0149,
        "100.0": 0.018000000000000002,
        "80.0": 0.0276,
        "130.0": 0.0022,
        "74.0": 0.03849999999999999,
        "34.0": 0.023,
        "82.0": 0.02,
        "18.0": 0.017499999999999998,
        "42.0": 0.0615,
        "66.0": 0.028099999999999997,
        "16.0": 0.0087,
        "106.0": 0.0045000000000000005,
        "50.0": 0.0308,
        "10.0": 0.021,
        "72.0": 0.0268,
        "173.0": 0.005,
        "101.0": 0.0312,
        "45.0": 0.0375,
        "117.0": 0.0108,
        "109.0": 0.0289,
        "53.0": 0.0148,
        "77.0": 0.047,
        "69.0": 0.0159,
        "2.0": 0.0116,
        "149.0": 0.0063999999999999994,
        "21.0": 0.0081,
        "37.0": 0.014499999999999999,
        "85.0": 0.0161,
        "128.0": 0.0056,
        "216.0": 0.0024,
        "144.0": 0.0137,
        "88.0": 0.0121,
        "136.0": 0.008199999999999999
    },
    "probability_distribution_items": [
        [
            64.0,
            0.0029
        ],
        [
            40.0,
            0.0158
        ],
        [
            97.0,
            0.0174
        ],
        [
            41.0,
            0.040999999999999995
        ],
        [
            1.0,
            0.008799999999999999
        ],
        [
            73.0,
            0.0519
        ],
        [
            81.0,
            0.015799999999999998
        ],
        [
            17.0,
            0.0153
        ],
        [
            65.0,
            0.0275
        ],
        [
            33.0,
            0.0172
        ],
        [
            9.0,
            0.0235
        ],
        [
            49.0,
            0.030100000000000002
        ],
        [
            105.0,
            0.0095
        ],
        [
            32.0,
            0.0086
        ],
        [
            140.0,
            0.0063
        ],
        [
            68.0,
            0.013600000000000001
        ],
        [
            12.0,
            0.005900000000000001
        ],
        [
            116.0,
            0.0127
        ],
        [
            108.0,
            0.0292
        ],
        [
            44.0,
            0.0141
        ],
        [
            52.0,
            0.0149
        ],
        [
            100.0,
            0.018000000000000002
        ],
        [
            80.0,
            0.0276
        ],
        [
            130.0,
            0.0022
        ],
        [
            74.0,
            0.03849999999999999
        ],
        [
            34.0,
            0.023
        ],
        [
            82.0,
            0.02
        ],
        [
            18.0,
            0.017499999999999998
        ],
        [
            42.0,
            0.0615
        ],
        [
            66.0,
            0.028099999999999997
        ],
        [
            16.0,
            0.0087
        ],
        [
            106.0,
            0.0045000000000000005
        ],
        [
            50.0,
            0.0308
        ],
        [
            10.0,
            0.021
        ],
        [
            72.0,
            0.0268
        ],
        [
            173.0,
            0.005
        ],
        [
            101.0,
            0.0312
        ],
        [
            45.0,
            0.0375
        ],
        [
            117.0,
            0.0108
        ],
        [
            109.0,
            0.0289
        ],
        [
            53.0,
            0.0148
        ],
        [
            77.0,
            0.047
        ],
        [
            69.0,
            0.0159
        ],
        [
            2.0,
            0.0116
        ],
        [
            149.0,
            0.0063999999999999994
        ],
        [
            21.0,
            0.0081
        ],
        [
            37.0,
            0.014499999999999999
        ],
        [
            85.0,
            0.0161
        ],
        [
            128.0,
            0.0056
        ],
        [
            216.0,
            0.0024
        ],
        [
            144.0,
            0.0137
        ],
        [
            88.0,
            0.0121
        ],
        [
            136.0,
            0.008199999999999999
        ]
    ],
    "approximation_ratio": 64.5442,
    "approximation_ratio_offset": 0.7044455813953489,
    "noise": true,
    "p": 7
}