{
    "expected_value": 39.3053,
    "optimal_gammas": [
        5.485364547861151,
        5.893887204534517,
        4.340577618027384,
        4.450951310808134
    ],
    "optimal_betas": [
        1.297888451703443,
        1.756844438190388,
        1.1313084020265043,
        1.4250050711583255
    ],
    "problem_identifier": "{'W': [1, 1], 'W_max': 2, 'A': 32, 'B': 4, 'C': 64}",
    "now": "2021-05-11 02:54:59",
    "execution_time": "2:02:28.234992",
    "nfev": 6372,
    "message": "Maximum number of iterations has been exceeded.",
    "success": false,
    "nit": 50,
    "routing": "network",
    "problem": {
        "W": [
            1,
            1
        ],
        "W_max": 2,
        "A": 32,
        "B": 4,
        "C": 64
    },
    "optimal_cost": 1.0,
    "probability_distribution": {
        "32.0": 0.0143,
        "24.0": 0.012499999999999999,
        "65.0": 0.017400000000000002,
        "25.0": 0.033900000000000007,
        "1.0": 0.0109,
        "57.0": 0.0198,
        "49.0": 0.0269,
        "17.0": 0.0293,
        "41.0": 0.0235,
        "9.0": 0.0227,
        "33.0": 0.0264,
        "73.0": 0.008199999999999999,
        "108.0": 0.0049,
        "52.0": 0.0142,
        "12.0": 0.0303,
        "100.0": 0.0052,
        "76.0": 0.0343,
        "44.0": 0.012400000000000001,
        "36.0": 0.0494,
        "84.0": 0.0086,
        "48.0": 0.0024000000000000002,
        "98.0": 0.0016,
        "58.0": 0.006699999999999999,
        "34.0": 0.059099999999999986,
        "50.0": 0.0213,
        "18.0": 0.0454,
        "26.0": 0.0407,
        "16.0": 0.0045000000000000005,
        "74.0": 0.003,
        "42.0": 0.05600000000000001,
        "10.0": 0.027,
        "56.0": 0.0215,
        "141.0": 0.0014,
        "85.0": 0.0074,
        "45.0": 0.0601,
        "101.0": 0.0038000000000000004,
        "77.0": 0.013,
        "37.0": 0.04409999999999999,
        "53.0": 0.057999999999999996,
        "2.0": 0.0039,
        "117.0": 0.0015,
        "61.0": 0.026099999999999998,
        "21.0": 0.0112,
        "93.0": 0.0042,
        "69.0": 0.009500000000000001,
        "29.0": 0.028999999999999998,
        "96.0": 0.0022,
        "184.0": 0.0004,
        "128.0": 0.0021,
        "88.0": 0.0036,
        "104.0": 0.0028,
        "72.0": 0.0034,
        "64.0": 0.018000000000000002
    },
    "probability_distribution_items": [
        [
            32.0,
            0.0143
        ],
        [
            24.0,
            0.012499999999999999
        ],
        [
            65.0,
            0.017400000000000002
        ],
        [
            25.0,
            0.033900000000000007
        ],
        [
            1.0,
            0.0109
        ],
        [
            57.0,
            0.0198
        ],
        [
            49.0,
            0.0269
        ],
        [
            17.0,
            0.0293
        ],
        [
            41.0,
            0.0235
        ],
        [
            9.0,
            0.0227
        ],
        [
            33.0,
            0.0264
        ],
        [
            73.0,
            0.008199999999999999
        ],
        [
            108.0,
            0.0049
        ],
        [
            52.0,
            0.0142
        ],
        [
            12.0,
            0.0303
        ],
        [
            100.0,
            0.0052
        ],
        [
            76.0,
            0.0343
        ],
        [
            44.0,
            0.012400000000000001
        ],
        [
            36.0,
            0.0494
        ],
        [
            84.0,
            0.0086
        ],
        [
            48.0,
            0.0024000000000000002
        ],
        [
            98.0,
            0.0016
        ],
        [
            58.0,
            0.006699999999999999
        ],
        [
            34.0,
            0.059099999999999986
        ],
        [
            50.0,
            0.0213
        ],
        [
            18.0,
            0.0454
        ],
        [
            26.0,
            0.0407
        ],
        [
            16.0,
            0.0045000000000000005
        ],
        [
            74.0,
            0.003
        ],
        [
            42.0,
            0.05600000000000001
        ],
        [
            10.0,
            0.027
        ],
        [
            56.0,
            0.0215
        ],
        [
            141.0,
            0.0014
        ],
        [
            85.0,
            0.0074
        ],
        [
            45.0,
            0.0601
        ],
        [
            101.0,
            0.0038000000000000004
        ],
        [
            77.0,
            0.013
        ],
        [
            37.0,
            0.04409999999999999
        ],
        [
            53.0,
            0.057999999999999996
        ],
        [
            2.0,
            0.0039
        ],
        [
            117.0,
            0.0015
        ],
        [
            61.0,
            0.026099999999999998
        ],
        [
            21.0,
            0.0112
        ],
        [
            93.0,
            0.0042
        ],
        [
            69.0,
            0.009500000000000001
        ],
        [
            29.0,
            0.028999999999999998
        ],
        [
            96.0,
            0.0022
        ],
        [
            184.0,
            0.0004
        ],
        [
            128.0,
            0.0021
        ],
        [
            88.0,
            0.0036
        ],
        [
            104.0,
            0.0028
        ],
        [
            72.0,
            0.0034
        ],
        [
            64.0,
            0.018000000000000002
        ]
    ],
    "approximation_ratio": 41.8373,
    "approximation_ratio_offset": 0.7768453551912569,
    "noise": false,
    "p": 4
}