{
    "expected_value": 207.0178,
    "optimal_gammas": [
        0.9525266634647944,
        2.674421869665588,
        0.5022376559833606,
        1.4713976384461456
    ],
    "optimal_betas": [
        2.0511946320407883,
        2.0405098032125695,
        2.6765466000613185,
        2.9321405666903457
    ],
    "problem_identifier": "{'W': [1, 1], 'W_max': 2, 'A': 40, 'B': 4, 'C': 720}",
    "now": "2021-05-04 21:38:38",
    "execution_time": "2:35:16.496868",
    "nfev": 8949,
    "message": "Optimization terminated successfully.",
    "success": true,
    "nit": 72
}