{
    "expected_value": 45.78050937316958,
    "optimal_gammas": [
        3.2676340262333756,
        4.193996057161369,
        2.504535477608224,
        1.4773720240408197
    ],
    "optimal_betas": [
        1.5887625571115096,
        2.1855273124877046,
        2.698492638207223,
        1.8515158088506247
    ],
    "problem_identifier": "{'W': [1, 1], 'W_max': 2, 'A': 32, 'B': 4, 'C': 128}",
    "now": "2021-05-07 23:47:10",
    "execution_time": "0:50:25.590490",
    "nfev": 6984,
    "message": "Maximum number of iterations has been exceeded.",
    "success": false,
    "nit": 50
}