{
    "expected_value": 413.307,
    "optimal_gammas": [
        1.724057616734298,
        0.3324741440530836,
        5.47864507061108,
        6.185811919876922,
        2.5667619856329207,
        2.327367642032804,
        0.23677440629971125
    ],
    "optimal_betas": [
        0.5390859493499682,
        1.558213675632099,
        1.3613049979317318,
        3.1343339170797195,
        0.6344808634309587,
        2.6397559944712983,
        2.6434924951023673
    ],
    "problem_identifier": "{'W': [1, 1], 'W_max': 2, 'A': 56, 'B': 4, 'C': 1456}",
    "now": "2021-05-04 17:29:30",
    "execution_time": "0:24:16.727214",
    "nfev": 825,
    "message": "Optimization terminated successfully.",
    "success": true,
    "nit": 1,
    "problem": {
        "W": [
            1,
            1
        ],
        "W_max": 2,
        "A": 56,
        "B": 4,
        "C": 1456
    },
    "probability_distribution": {
        "728.0": 0.0057,
        "378.0": 0.027500000000000004,
        "785.0": 0.0152,
        "379.0": 0.0359,
        "1.0": 0.0072,
        "435.0": 0.0326,
        "757.0": 0.021900000000000003,
        "29.0": 0.0218,
        "113.0": 0.006500000000000001,
        "743.0": 0.032,
        "365.0": 0.0244,
        "15.0": 0.0293,
        "393.0": 0.0371,
        "71.0": 0.0082,
        "421.0": 0.017099999999999997,
        "799.0": 0.0086,
        "56.0": 0.0089,
        "858.0": 0.007599999999999999,
        "424.0": 0.0199,
        "18.0": 0.0083,
        "508.0": 0.0158,
        "802.0": 0.0213,
        "74.0": 0.018099999999999998,
        "396.0": 0.0162,
        "186.0": 0.0072,
        "480.0": 0.0155,
        "756.0": 0.0132,
        "842.0": 0.0031,
        "436.0": 0.0143,
        "58.0": 0.0052,
        "758.0": 0.0168,
        "30.0": 0.018099999999999998,
        "380.0": 0.04549999999999999,
        "730.0": 0.012299999999999998,
        "28.0": 0.011099999999999999,
        "800.0": 0.0065,
        "422.0": 0.012900000000000002,
        "72.0": 0.0056,
        "394.0": 0.0292,
        "744.0": 0.0229,
        "16.0": 0.0246,
        "366.0": 0.0143,
        "434.0": 0.0192,
        "915.0": 0.0054,
        "481.0": 0.011200000000000002,
        "75.0": 0.017,
        "509.0": 0.0122,
        "803.0": 0.012299999999999998,
        "397.0": 0.0114,
        "131.0": 0.0060999999999999995,
        "425.0": 0.0112,
        "747.0": 0.0059,
        "2.0": 0.009899999999999999,
        "873.0": 0.0060999999999999995,
        "439.0": 0.0265,
        "33.0": 0.0048000000000000004,
        "495.0": 0.015500000000000002,
        "789.0": 0.013600000000000001,
        "61.0": 0.014199999999999999,
        "383.0": 0.0126,
        "145.0": 0.0059,
        "761.0": 0.0054,
        "840.0": 0.0056,
        "988.0": 0.0022,
        "554.0": 0.0135,
        "148.0": 0.004999999999999999,
        "848.0": 0.0051,
        "120.0": 0.0059,
        "442.0": 0.008799999999999999,
        "764.0": 0.0021
    },
    "probability_distribution_items": [
        [
            728.0,
            0.0057
        ],
        [
            378.0,
            0.027500000000000004
        ],
        [
            785.0,
            0.0152
        ],
        [
            379.0,
            0.0359
        ],
        [
            1.0,
            0.0072
        ],
        [
            435.0,
            0.0326
        ],
        [
            757.0,
            0.021900000000000003
        ],
        [
            29.0,
            0.0218
        ],
        [
            113.0,
            0.006500000000000001
        ],
        [
            743.0,
            0.032
        ],
        [
            365.0,
            0.0244
        ],
        [
            15.0,
            0.0293
        ],
        [
            393.0,
            0.0371
        ],
        [
            71.0,
            0.0082
        ],
        [
            421.0,
            0.017099999999999997
        ],
        [
            799.0,
            0.0086
        ],
        [
            56.0,
            0.0089
        ],
        [
            858.0,
            0.007599999999999999
        ],
        [
            424.0,
            0.0199
        ],
        [
            18.0,
            0.0083
        ],
        [
            508.0,
            0.0158
        ],
        [
            802.0,
            0.0213
        ],
        [
            74.0,
            0.018099999999999998
        ],
        [
            396.0,
            0.0162
        ],
        [
            186.0,
            0.0072
        ],
        [
            480.0,
            0.0155
        ],
        [
            756.0,
            0.0132
        ],
        [
            842.0,
            0.0031
        ],
        [
            436.0,
            0.0143
        ],
        [
            58.0,
            0.0052
        ],
        [
            758.0,
            0.0168
        ],
        [
            30.0,
            0.018099999999999998
        ],
        [
            380.0,
            0.04549999999999999
        ],
        [
            730.0,
            0.012299999999999998
        ],
        [
            28.0,
            0.011099999999999999
        ],
        [
            800.0,
            0.0065
        ],
        [
            422.0,
            0.012900000000000002
        ],
        [
            72.0,
            0.0056
        ],
        [
            394.0,
            0.0292
        ],
        [
            744.0,
            0.0229
        ],
        [
            16.0,
            0.0246
        ],
        [
            366.0,
            0.0143
        ],
        [
            434.0,
            0.0192
        ],
        [
            915.0,
            0.0054
        ],
        [
            481.0,
            0.011200000000000002
        ],
        [
            75.0,
            0.017
        ],
        [
            509.0,
            0.0122
        ],
        [
            803.0,
            0.012299999999999998
        ],
        [
            397.0,
            0.0114
        ],
        [
            131.0,
            0.0060999999999999995
        ],
        [
            425.0,
            0.0112
        ],
        [
            747.0,
            0.0059
        ],
        [
            2.0,
            0.009899999999999999
        ],
        [
            873.0,
            0.0060999999999999995
        ],
        [
            439.0,
            0.0265
        ],
        [
            33.0,
            0.0048000000000000004
        ],
        [
            495.0,
            0.015500000000000002
        ],
        [
            789.0,
            0.013600000000000001
        ],
        [
            61.0,
            0.014199999999999999
        ],
        [
            383.0,
            0.0126
        ],
        [
            145.0,
            0.0059
        ],
        [
            761.0,
            0.0054
        ],
        [
            840.0,
            0.0056
        ],
        [
            988.0,
            0.0022
        ],
        [
            554.0,
            0.0135
        ],
        [
            148.0,
            0.004999999999999999
        ],
        [
            848.0,
            0.0051
        ],
        [
            120.0,
            0.0059
        ],
        [
            442.0,
            0.008799999999999999
        ],
        [
            764.0,
            0.0021
        ]
    ],
    "approximation_ratio": 0.5758579533941236,
    "noise": true,
    "p": 7
}