{
    "expected_value": 58.9763,
    "optimal_gammas": [
        0.8726045735829397
    ],
    "optimal_betas": [
        0.47085316452240855
    ],
    "problem_identifier": "{'W': [1, 1], 'W_max': 2, 'A': 8, 'B': 4, 'C': 208}",
    "now": "2021-05-04 18:05:43",
    "execution_time": "0:07:02.684983",
    "nfev": 912,
    "message": "Optimization terminated successfully.",
    "success": true,
    "nit": 24,
    "problem": {
        "W": [
            1,
            1
        ],
        "W_max": 2,
        "A": 8,
        "B": 4,
        "C": 208
    },
    "optimal_cost": 1.0,
    "probability_distribution": {
        "104.0": 0.059,
        "54.0": 0.0393,
        "113.0": 0.05360000000000001,
        "55.0": 0.0414,
        "1.0": 0.04,
        "63.0": 0.012499999999999997,
        "109.0": 0.0050999999999999995,
        "5.0": 0.0036,
        "17.0": 0.0040999999999999995,
        "107.0": 0.0322,
        "53.0": 0.031799999999999995,
        "3.0": 0.0406,
        "57.0": 0.0208,
        "11.0": 0.0027,
        "61.0": 0.024300000000000002,
        "115.0": 0.0031999999999999997,
        "8.0": 0.011699999999999999,
        "126.0": 0.006999999999999999,
        "64.0": 0.0364,
        "6.0": 0.06709999999999999,
        "76.0": 0.0022,
        "118.0": 0.0082,
        "14.0": 0.0017000000000000001,
        "60.0": 0.016300000000000002,
        "30.0": 0.001,
        "72.0": 0.0015,
        "108.0": 0.012799999999999997,
        "122.0": 0.0122,
        "10.0": 0.0202,
        "110.0": 0.0229,
        "56.0": 0.0547,
        "106.0": 0.014400000000000001,
        "4.0": 0.0133,
        "116.0": 0.0393,
        "62.0": 0.0123,
        "12.0": 0.0084,
        "58.0": 0.017499999999999998,
        "135.0": 0.0017000000000000001,
        "73.0": 0.009399999999999999,
        "15.0": 0.0309,
        "77.0": 0.0015999999999999999,
        "119.0": 0.0039,
        "23.0": 0.0037,
        "65.0": 0.0066,
        "111.0": 0.0211,
        "2.0": 0.0043,
        "129.0": 0.0031000000000000003,
        "67.0": 0.0175,
        "9.0": 0.0316,
        "75.0": 0.0029,
        "117.0": 0.0031999999999999997,
        "13.0": 0.0043,
        "59.0": 0.022099999999999998,
        "25.0": 0.0031999999999999997,
        "120.0": 0.0005,
        "148.0": 0.0004,
        "86.0": 0.0014,
        "28.0": 0.0058,
        "128.0": 0.0019,
        "24.0": 0.0017000000000000001,
        "70.0": 0.021900000000000003
    },
    "probability_distribution_items": [
        [
            104.0,
            0.059
        ],
        [
            54.0,
            0.0393
        ],
        [
            113.0,
            0.05360000000000001
        ],
        [
            55.0,
            0.0414
        ],
        [
            1.0,
            0.04
        ],
        [
            63.0,
            0.012499999999999997
        ],
        [
            109.0,
            0.0050999999999999995
        ],
        [
            5.0,
            0.0036
        ],
        [
            17.0,
            0.0040999999999999995
        ],
        [
            107.0,
            0.0322
        ],
        [
            53.0,
            0.031799999999999995
        ],
        [
            3.0,
            0.0406
        ],
        [
            57.0,
            0.0208
        ],
        [
            11.0,
            0.0027
        ],
        [
            61.0,
            0.024300000000000002
        ],
        [
            115.0,
            0.0031999999999999997
        ],
        [
            8.0,
            0.011699999999999999
        ],
        [
            126.0,
            0.006999999999999999
        ],
        [
            64.0,
            0.0364
        ],
        [
            6.0,
            0.06709999999999999
        ],
        [
            76.0,
            0.0022
        ],
        [
            118.0,
            0.0082
        ],
        [
            14.0,
            0.0017000000000000001
        ],
        [
            60.0,
            0.016300000000000002
        ],
        [
            30.0,
            0.001
        ],
        [
            72.0,
            0.0015
        ],
        [
            108.0,
            0.012799999999999997
        ],
        [
            122.0,
            0.0122
        ],
        [
            10.0,
            0.0202
        ],
        [
            110.0,
            0.0229
        ],
        [
            56.0,
            0.0547
        ],
        [
            106.0,
            0.014400000000000001
        ],
        [
            4.0,
            0.0133
        ],
        [
            116.0,
            0.0393
        ],
        [
            62.0,
            0.0123
        ],
        [
            12.0,
            0.0084
        ],
        [
            58.0,
            0.017499999999999998
        ],
        [
            135.0,
            0.0017000000000000001
        ],
        [
            73.0,
            0.009399999999999999
        ],
        [
            15.0,
            0.0309
        ],
        [
            77.0,
            0.0015999999999999999
        ],
        [
            119.0,
            0.0039
        ],
        [
            23.0,
            0.0037
        ],
        [
            65.0,
            0.0066
        ],
        [
            111.0,
            0.0211
        ],
        [
            2.0,
            0.0043
        ],
        [
            129.0,
            0.0031000000000000003
        ],
        [
            67.0,
            0.0175
        ],
        [
            9.0,
            0.0316
        ],
        [
            75.0,
            0.0029
        ],
        [
            117.0,
            0.0031999999999999997
        ],
        [
            13.0,
            0.0043
        ],
        [
            59.0,
            0.022099999999999998
        ],
        [
            25.0,
            0.0031999999999999997
        ],
        [
            120.0,
            0.0005
        ],
        [
            148.0,
            0.0004
        ],
        [
            86.0,
            0.0014
        ],
        [
            28.0,
            0.0058
        ],
        [
            128.0,
            0.0019
        ],
        [
            24.0,
            0.0017000000000000001
        ],
        [
            70.0,
            0.021900000000000003
        ]
    ],
    "approximation_ratio": 59.9753,
    "approximation_ratio_offset": 0.5988074829931973,
    "noise": true,
    "p": 1
}