{
    "expected_value": 123.573,
    "optimal_gammas": [
        1.8688905712467592
    ],
    "optimal_betas": [
        2.84861135575757
    ],
    "problem_identifier": "{'W': [1, 1], 'W_max': 2, 'A': 40, 'B': 4, 'C': 400}",
    "now": "2021-05-04 17:56:24",
    "execution_time": "0:12:25.819219",
    "nfev": 1596,
    "message": "Optimization terminated successfully.",
    "success": true,
    "nit": 50,
    "problem": {
        "W": [
            1,
            1
        ],
        "W_max": 2,
        "A": 40,
        "B": 4,
        "C": 400
    },
    "optimal_cost": 1.0,
    "probability_distribution": {
        "200.0": 0.0281,
        "110.0": 0.029199999999999997,
        "241.0": 0.022299999999999997,
        "111.0": 0.0625,
        "1.0": 0.0165,
        "151.0": 0.014199999999999999,
        "221.0": 0.015099999999999999,
        "21.0": 0.013000000000000001,
        "81.0": 0.0019,
        "211.0": 0.037,
        "101.0": 0.052899999999999996,
        "11.0": 0.0286,
        "121.0": 0.0207,
        "51.0": 0.0007,
        "141.0": 0.002,
        "251.0": 0.0012,
        "40.0": 0.0029,
        "294.0": 0.0029,
        "144.0": 0.0274,
        "14.0": 0.0409,
        "204.0": 0.0016,
        "254.0": 0.0074,
        "54.0": 0.0109,
        "124.0": 0.0211,
        "134.0": 0.0001,
        "184.0": 0.0021,
        "220.0": 0.0064,
        "282.0": 0.003,
        "152.0": 0.0154,
        "42.0": 0.006500000000000001,
        "222.0": 0.0157,
        "22.0": 0.0159,
        "112.0": 0.045399999999999996,
        "202.0": 0.014499999999999999,
        "20.0": 0.0023,
        "252.0": 0.0079,
        "142.0": 0.022600000000000002,
        "52.0": 0.0060999999999999995,
        "122.0": 0.035199999999999995,
        "212.0": 0.031,
        "12.0": 0.035,
        "102.0": 0.0167,
        "150.0": 0.0015999999999999999,
        "335.0": 0.0016,
        "185.0": 0.0102,
        "55.0": 0.0251,
        "205.0": 0.0023,
        "255.0": 0.0134,
        "125.0": 0.0351,
        "95.0": 0.0005,
        "145.0": 0.0067,
        "215.0": 0.0126,
        "2.0": 0.0114,
        "305.0": 0.0009000000000000001,
        "155.0": 0.016499999999999997,
        "25.0": 0.0108,
        "195.0": 0.0028,
        "245.0": 0.0121,
        "45.0": 0.0102,
        "115.0": 0.0337,
        "105.0": 0.0007,
        "225.0": 0.010100000000000001,
        "280.0": 0.0001,
        "388.0": 0.0001,
        "238.0": 0.0012000000000000001,
        "108.0": 0.0018999999999999998,
        "288.0": 0.005,
        "88.0": 0.0025,
        "158.0": 0.0175,
        "228.0": 0.0106
    },
    "probability_distribution_items": [
        [
            200.0,
            0.0281
        ],
        [
            110.0,
            0.029199999999999997
        ],
        [
            241.0,
            0.022299999999999997
        ],
        [
            111.0,
            0.0625
        ],
        [
            1.0,
            0.0165
        ],
        [
            151.0,
            0.014199999999999999
        ],
        [
            221.0,
            0.015099999999999999
        ],
        [
            21.0,
            0.013000000000000001
        ],
        [
            81.0,
            0.0019
        ],
        [
            211.0,
            0.037
        ],
        [
            101.0,
            0.052899999999999996
        ],
        [
            11.0,
            0.0286
        ],
        [
            121.0,
            0.0207
        ],
        [
            51.0,
            0.0007
        ],
        [
            141.0,
            0.002
        ],
        [
            251.0,
            0.0012
        ],
        [
            40.0,
            0.0029
        ],
        [
            294.0,
            0.0029
        ],
        [
            144.0,
            0.0274
        ],
        [
            14.0,
            0.0409
        ],
        [
            204.0,
            0.0016
        ],
        [
            254.0,
            0.0074
        ],
        [
            54.0,
            0.0109
        ],
        [
            124.0,
            0.0211
        ],
        [
            134.0,
            0.0001
        ],
        [
            184.0,
            0.0021
        ],
        [
            220.0,
            0.0064
        ],
        [
            282.0,
            0.003
        ],
        [
            152.0,
            0.0154
        ],
        [
            42.0,
            0.006500000000000001
        ],
        [
            222.0,
            0.0157
        ],
        [
            22.0,
            0.0159
        ],
        [
            112.0,
            0.045399999999999996
        ],
        [
            202.0,
            0.014499999999999999
        ],
        [
            20.0,
            0.0023
        ],
        [
            252.0,
            0.0079
        ],
        [
            142.0,
            0.022600000000000002
        ],
        [
            52.0,
            0.0060999999999999995
        ],
        [
            122.0,
            0.035199999999999995
        ],
        [
            212.0,
            0.031
        ],
        [
            12.0,
            0.035
        ],
        [
            102.0,
            0.0167
        ],
        [
            150.0,
            0.0015999999999999999
        ],
        [
            335.0,
            0.0016
        ],
        [
            185.0,
            0.0102
        ],
        [
            55.0,
            0.0251
        ],
        [
            205.0,
            0.0023
        ],
        [
            255.0,
            0.0134
        ],
        [
            125.0,
            0.0351
        ],
        [
            95.0,
            0.0005
        ],
        [
            145.0,
            0.0067
        ],
        [
            215.0,
            0.0126
        ],
        [
            2.0,
            0.0114
        ],
        [
            305.0,
            0.0009000000000000001
        ],
        [
            155.0,
            0.016499999999999997
        ],
        [
            25.0,
            0.0108
        ],
        [
            195.0,
            0.0028
        ],
        [
            245.0,
            0.0121
        ],
        [
            45.0,
            0.0102
        ],
        [
            115.0,
            0.0337
        ],
        [
            105.0,
            0.0007
        ],
        [
            225.0,
            0.010100000000000001
        ],
        [
            280.0,
            0.0001
        ],
        [
            388.0,
            0.0001
        ],
        [
            238.0,
            0.0012000000000000001
        ],
        [
            108.0,
            0.0018999999999999998
        ],
        [
            288.0,
            0.005
        ],
        [
            88.0,
            0.0025
        ],
        [
            158.0,
            0.0175
        ],
        [
            228.0,
            0.0106
        ]
    ],
    "approximation_ratio": 126.4534,
    "approximation_ratio_offset": 0.675831007751938,
    "noise": true,
    "p": 1
}