{
    "expected_value": 124.021,
    "optimal_gammas": [
        1.869261700292169
    ],
    "optimal_betas": [
        2.8082825901841906
    ],
    "problem_identifier": "{'W': [1, 1], 'W_max': 2, 'A': 40, 'B': 4, 'C': 400}",
    "now": "2021-05-04 18:39:23",
    "execution_time": "0:17:23.996348",
    "nfev": 1977,
    "message": "Optimization terminated successfully.",
    "success": true,
    "nit": 61,
    "problem": {
        "W": [
            1,
            1
        ],
        "W_max": 2,
        "A": 40,
        "B": 4,
        "C": 400
    },
    "optimal_cost": 1.0,
    "probability_distribution": {
        "200.0": 0.0293,
        "110.0": 0.0336,
        "241.0": 0.0217,
        "111.0": 0.0618,
        "1.0": 0.0179,
        "151.0": 0.0154,
        "221.0": 0.0149,
        "21.0": 0.0133,
        "81.0": 0.0007,
        "211.0": 0.0349,
        "101.0": 0.0539,
        "11.0": 0.0336,
        "121.0": 0.0198,
        "51.0": 0.0014999999999999998,
        "141.0": 0.002,
        "251.0": 0.0007,
        "40.0": 0.0035,
        "294.0": 0.0035,
        "144.0": 0.025500000000000002,
        "14.0": 0.0353,
        "204.0": 0.0023,
        "254.0": 0.007300000000000001,
        "54.0": 0.009600000000000001,
        "124.0": 0.0227,
        "134.0": 0.0004,
        "184.0": 0.0011,
        "220.0": 0.0056,
        "282.0": 0.0031,
        "152.0": 0.019,
        "42.0": 0.0063999999999999994,
        "222.0": 0.016300000000000002,
        "22.0": 0.017499999999999998,
        "112.0": 0.0505,
        "202.0": 0.0138,
        "20.0": 0.0031000000000000003,
        "252.0": 0.0074,
        "142.0": 0.0176,
        "52.0": 0.006200000000000001,
        "122.0": 0.0314,
        "212.0": 0.0262,
        "12.0": 0.0281,
        "102.0": 0.0162,
        "150.0": 0.0015999999999999999,
        "335.0": 0.0015999999999999999,
        "185.0": 0.0087,
        "55.0": 0.023299999999999998,
        "205.0": 0.0026000000000000003,
        "255.0": 0.012199999999999999,
        "125.0": 0.0354,
        "95.0": 0.0005,
        "145.0": 0.0068000000000000005,
        "215.0": 0.0111,
        "2.0": 0.012199999999999999,
        "305.0": 0.0007999999999999999,
        "155.0": 0.0158,
        "25.0": 0.014,
        "195.0": 0.0029000000000000002,
        "245.0": 0.012900000000000002,
        "45.0": 0.013000000000000001,
        "115.0": 0.0348,
        "105.0": 0.0011,
        "225.0": 0.013600000000000001,
        "280.0": 0.0001,
        "238.0": 0.0019000000000000002,
        "108.0": 0.002,
        "288.0": 0.004,
        "88.0": 0.0029,
        "158.0": 0.0166,
        "228.0": 0.013
    },
    "probability_distribution_items": [
        [
            200.0,
            0.0293
        ],
        [
            110.0,
            0.0336
        ],
        [
            241.0,
            0.0217
        ],
        [
            111.0,
            0.0618
        ],
        [
            1.0,
            0.0179
        ],
        [
            151.0,
            0.0154
        ],
        [
            221.0,
            0.0149
        ],
        [
            21.0,
            0.0133
        ],
        [
            81.0,
            0.0007
        ],
        [
            211.0,
            0.0349
        ],
        [
            101.0,
            0.0539
        ],
        [
            11.0,
            0.0336
        ],
        [
            121.0,
            0.0198
        ],
        [
            51.0,
            0.0014999999999999998
        ],
        [
            141.0,
            0.002
        ],
        [
            251.0,
            0.0007
        ],
        [
            40.0,
            0.0035
        ],
        [
            294.0,
            0.0035
        ],
        [
            144.0,
            0.025500000000000002
        ],
        [
            14.0,
            0.0353
        ],
        [
            204.0,
            0.0023
        ],
        [
            254.0,
            0.007300000000000001
        ],
        [
            54.0,
            0.009600000000000001
        ],
        [
            124.0,
            0.0227
        ],
        [
            134.0,
            0.0004
        ],
        [
            184.0,
            0.0011
        ],
        [
            220.0,
            0.0056
        ],
        [
            282.0,
            0.0031
        ],
        [
            152.0,
            0.019
        ],
        [
            42.0,
            0.0063999999999999994
        ],
        [
            222.0,
            0.016300000000000002
        ],
        [
            22.0,
            0.017499999999999998
        ],
        [
            112.0,
            0.0505
        ],
        [
            202.0,
            0.0138
        ],
        [
            20.0,
            0.0031000000000000003
        ],
        [
            252.0,
            0.0074
        ],
        [
            142.0,
            0.0176
        ],
        [
            52.0,
            0.006200000000000001
        ],
        [
            122.0,
            0.0314
        ],
        [
            212.0,
            0.0262
        ],
        [
            12.0,
            0.0281
        ],
        [
            102.0,
            0.0162
        ],
        [
            150.0,
            0.0015999999999999999
        ],
        [
            335.0,
            0.0015999999999999999
        ],
        [
            185.0,
            0.0087
        ],
        [
            55.0,
            0.023299999999999998
        ],
        [
            205.0,
            0.0026000000000000003
        ],
        [
            255.0,
            0.012199999999999999
        ],
        [
            125.0,
            0.0354
        ],
        [
            95.0,
            0.0005
        ],
        [
            145.0,
            0.0068000000000000005
        ],
        [
            215.0,
            0.0111
        ],
        [
            2.0,
            0.012199999999999999
        ],
        [
            305.0,
            0.0007999999999999999
        ],
        [
            155.0,
            0.0158
        ],
        [
            25.0,
            0.014
        ],
        [
            195.0,
            0.0029000000000000002
        ],
        [
            245.0,
            0.012900000000000002
        ],
        [
            45.0,
            0.013000000000000001
        ],
        [
            115.0,
            0.0348
        ],
        [
            105.0,
            0.0011
        ],
        [
            225.0,
            0.013600000000000001
        ],
        [
            280.0,
            0.0001
        ],
        [
            238.0,
            0.0019000000000000002
        ],
        [
            108.0,
            0.002
        ],
        [
            288.0,
            0.004
        ],
        [
            88.0,
            0.0029
        ],
        [
            158.0,
            0.0166
        ],
        [
            228.0,
            0.013
        ]
    ],
    "approximation_ratio": 126.3188,
    "approximation_ratio_offset": 0.6247940119760479,
    "noise": true,
    "p": 1
}