{
    "expected_value": 1.0000000000005211,
    "optimal_gammas": [
        3.7306413342003726,
        1.7671458345470188
    ],
    "optimal_betas": [
        1.570796982655344,
        2.3561942963446736
    ],
    "problem_identifier": "{'W': [1], 'W_max': 1, 'A': 8, 'B': 4, 'C': 12}",
    "now": "2021-05-05 06:20:35",
    "execution_time": "3:16:34.123035",
    "nfev": 6790,
    "message": "Optimization terminated successfully.",
    "success": true,
    "nit": 111,
    "problem": {
        "W": [
            1
        ],
        "W_max": 1,
        "A": 8,
        "B": 4,
        "C": 12
    },
    "probability_distribution": {
        "3.0": 2.49303864482969e-15,
        "2.0": 3.2022578488355334e-13,
        "6.0": 3.9180610176993055e-14,
        "1.0": 0.9999999999996381
    },
    "probability_distribution_items": [
        [
            3.0,
            2.49303864482969e-15
        ],
        [
            2.0,
            3.2022578488355334e-13
        ],
        [
            6.0,
            3.9180610176993055e-14
        ],
        [
            1.0,
            0.9999999999996381
        ]
    ],
    "approximation_ratio": 0.9999999999998958,
    "noise": false,
    "p": 2
}